summ/__about__.py
summ/__init__.py
summ/pipeline.py
summ/summ.py
summ/cache/__init__.py
summ/cache/cacher.py
summ/classify/__init__.py
summ/classify/classes.py
summ/classify/classifier.py
summ/cli/__init__.py
summ/cli/app.py
summ/cli/cli.py
summ/cli/styles.css
summ/cli/utils.py
summ/cli/screens/__init__.py
summ/cli/screens/main.py
summ/cli/screens/screen.py
summ/cli/screens/settings.py
summ/cli/screens/welcome.py
summ/cli/widgets/__init__.py
summ/cli/widgets/file.py
summ/cli/widgets/home.py
summ/cli/widgets/input_with_label.py
summ/cli/widgets/output_tree.py
summ/cli/widgets/reactive_tree.py
summ/embed/__init__.py
summ/embed/embedder.py
summ/examples/__init__.py
summ/examples/otter/README.md
summ/examples/otter/__init__.py
summ/examples/otter/implementation/__init__.py
summ/examples/otter/implementation/__main__.py
summ/examples/otter/implementation/classes.py
summ/examples/otter/implementation/classifier.py
summ/examples/otter/interviews/2022_cronutt_audio_final_otter_ai.txt
summ/examples/otter/interviews/9cbb258e-1134-df63-70c5-ecbcd282ce9b_otter_ai.txt
summ/examples/otter/interviews/fpuaa88i9zrerh9qhb902fsms19h_otter_ai.txt
summ/examples/otter/tests/__init__.py
summ/examples/otter/tests/test_example.py
summ/factify/__init__.py
summ/factify/factifier.py
summ/importers/__init__.py
summ/importers/importer.py
summ/query/__init__.py
summ/query/querier.py
summ/shared/__init__.py
summ/shared/chain.py
summ/shared/models.py
summ/shared/utils.py
summ/splitter/__init__.py
summ/splitter/gpt_splitter.py
summ/splitter/otter.py
summ/splitter/splitter.py
summ/structure/__init__.py
summ/structure/sql_structurer.py
summ/structure/structurer.py
summ/summarize/__init__.py
summ/summarize/summarizer.py
summ/tools/__init__.py
summ/tools/cli.py
summ/tools/example.py
summ-0.1.17.dist-info/METADATA
summ-0.1.17.dist-info/WHEEL
summ-0.1.17.dist-info/entry_points.txt
summ-0.1.17.dist-info/licenses/LICENSE.txt
summ-0.1.17.dist-info/RECORD
