Metadata-Version: 2.1
Name: summ
Version: 0.1.17
Summary: Summ provides intelligent question-answering and search capabilities across user interview transcripts.
Project-URL: Documentation, https://github.com/yasyf/summ#readme
Project-URL: Issues, https://github.com/yasyf/summ/issues
Project-URL: Source, https://github.com/yasyf/summ
Author-email: Yasyf Mohamedali <yasyfm+pypi@gmail.com>, Markie Wagner <me@markiewagner.com>
License-Expression: AGPL-3.0-only
License-File: LICENSE.txt
Classifier: Development Status :: 4 - Beta
Classifier: Programming Language :: Python
Classifier: Programming Language :: Python :: 3.11
Classifier: Programming Language :: Python :: Implementation :: CPython
Classifier: Programming Language :: Python :: Implementation :: PyPy
Requires-Python: >=3.11
Requires-Dist: click
Requires-Dist: dirtyjson
Requires-Dist: gitpython
Requires-Dist: jinja2
Requires-Dist: joblib
Requires-Dist: langchain==0.0.113
Requires-Dist: metrohash
Requires-Dist: openai
Requires-Dist: pinecone-client
Requires-Dist: pyperclip
Requires-Dist: python-dotenv
Requires-Dist: redis-om
Requires-Dist: redis[hiredis]
Requires-Dist: retry
Requires-Dist: termcolor
Requires-Dist: textual==0.15.1
Requires-Dist: tiktoken
